sortlib
sortlib_cpp
