Metadata-Version: 2.4
Name: interview_motoko_sortlib
Version: 0.2.0
Requires-Dist: pybind11>=2.10.0
Requires-Dist: numpy>=1.23.0
Requires-Dist: requests
Dynamic: requires-dist
